east_asian_spacing/__init__.py
east_asian_spacing/__main__.py
east_asian_spacing/builder.py
east_asian_spacing/config.py
east_asian_spacing/dump.py
east_asian_spacing/font.py
east_asian_spacing/shaper.py
east_asian_spacing/spacing.py
east_asian_spacing/tester.py
east_asian_spacing/ttc.py
east_asian_spacing/utils.py
east_asian_spacing-1.4.5.dist-info/METADATA
east_asian_spacing-1.4.5.dist-info/WHEEL
east_asian_spacing-1.4.5.dist-info/entry_points.txt
east_asian_spacing-1.4.5.dist-info/licenses/LICENSE
east_asian_spacing-1.4.5.dist-info/RECORD
