Metadata-Version: 2.4
Name: east_asian_spacing
Version: 1.4.5
Summary: East Asian Contextual Spacing Build Tools
Project-URL: repository, https://github.com/kojiishi/east_asian_spacing
Author-email: Koji Ishii <kojii@chromium.org>
License-Expression: Apache-2.0
License-File: LICENSE
Requires-Python: >=3.10
Requires-Dist: fonttools[woff]>=4.57.0
Requires-Dist: uharfbuzz>=0.50.2
